nestedobjects/DependentObjects.py
nestedobjects/NestedObjects.py
nestedobjects/__init__.py
nestedobjects-0.0.2.dist-info/LICENSE.txt
nestedobjects-0.0.2.dist-info/METADATA
nestedobjects-0.0.2.dist-info/WHEEL
nestedobjects-0.0.2.dist-info/top_level.txt
nestedobjects-0.0.2.dist-info/RECORD
