Metadata-Version: 2.1
Name: nestedobjects
Version: 0.0.2
Summary: creates an excel with all the dependent objects in a powerbi datasets or analysis services
Author: vamshi krishna
Author-email: vamshikrishna.r@sonata-software.com
Keywords: nested measures,dependent objects,dependent
Classifier: Development Status :: 1 - Planning
Classifier: Intended Audience :: Developers
Classifier: Programming Language :: Python :: 3
Classifier: Operating System :: Unix
Classifier: Operating System :: MacOS :: MacOS X
Classifier: Operating System :: Microsoft :: Windows
License-File: LICENSE.txt
Requires-Dist: pandas
Requires-Dist: pyadomd
